ElasticsearchQuanweiZhinan/README.md
ElasticsearchQuanweiZhinan/__init__.py
ElasticsearchQuanweiZhinan/__main__.py
ElasticsearchQuanweiZhinan/file.epub
ElasticsearchQuanweiZhinan/index.html
ElasticsearchQuanweiZhinan/css/__init__.py
ElasticsearchQuanweiZhinan/css/annotations.css
ElasticsearchQuanweiZhinan/css/main.css
ElasticsearchQuanweiZhinan/css/normalize.css
ElasticsearchQuanweiZhinan/css/popup.css
ElasticsearchQuanweiZhinan/font/__init__.py
ElasticsearchQuanweiZhinan/font/fontello.eot
ElasticsearchQuanweiZhinan/font/fontello.svg
ElasticsearchQuanweiZhinan/font/fontello.ttf
ElasticsearchQuanweiZhinan/font/fontello.woff
ElasticsearchQuanweiZhinan/img/__init__.py
ElasticsearchQuanweiZhinan/img/annotator-glyph-sprite.png
ElasticsearchQuanweiZhinan/img/annotator-icon-sprite.png
ElasticsearchQuanweiZhinan/img/apple-touch-icon.png
ElasticsearchQuanweiZhinan/img/cancelfullscreen.png
ElasticsearchQuanweiZhinan/img/close.png
ElasticsearchQuanweiZhinan/img/fullscreen.png
ElasticsearchQuanweiZhinan/img/loader.gif
ElasticsearchQuanweiZhinan/img/menu-icon.png
ElasticsearchQuanweiZhinan/img/save.png
ElasticsearchQuanweiZhinan/img/saved.png
ElasticsearchQuanweiZhinan/img/settings-s.png
ElasticsearchQuanweiZhinan/img/settings.png
ElasticsearchQuanweiZhinan/img/star.png
ElasticsearchQuanweiZhinan/js/__init__.py
ElasticsearchQuanweiZhinan/js/epub.js
ElasticsearchQuanweiZhinan/js/epub.min.js
ElasticsearchQuanweiZhinan/js/epub.min.map
ElasticsearchQuanweiZhinan/js/hooks.min.js
ElasticsearchQuanweiZhinan/js/hooks.min.map
ElasticsearchQuanweiZhinan/js/reader.js
ElasticsearchQuanweiZhinan/js/reader.js.map
ElasticsearchQuanweiZhinan/js/reader.min.js
ElasticsearchQuanweiZhinan/js/reader.min.map
ElasticsearchQuanweiZhinan/js/hooks/__init__.py
ElasticsearchQuanweiZhinan/js/hooks/extensions/__init__.py
ElasticsearchQuanweiZhinan/js/hooks/extensions/highlight.js
ElasticsearchQuanweiZhinan/js/libs/__init__.py
ElasticsearchQuanweiZhinan/js/libs/jquery.min.js
elasticsearch_quanwei_zhinan-2024.3.1.0.dist-info/METADATA
elasticsearch_quanwei_zhinan-2024.3.1.0.dist-info/WHEEL
elasticsearch_quanwei_zhinan-2024.3.1.0.dist-info/entry_points.txt
elasticsearch_quanwei_zhinan-2024.3.1.0.dist-info/top_level.txt
elasticsearch_quanwei_zhinan-2024.3.1.0.dist-info/RECORD
